{
  "assignee": "Jason Allum",
  "blocked_by": [
    "fz-a5z"
  ],
  "blocks": [
    "fz-vy7"
  ],
  "created": "2026-05-17T23:33:21Z",
  "description": "## Goal\n\nThe atomic move: typer, SpecRegistry, and codegen all switch off the\nper-callsite model in a single commit. Intermediate state is\nuncompilable, so this is one ticket. Regenerate 100 goldens. Measure\nCLIF size delta and fixture_matrix wall delta.\n\nReads what fz-7ot.1 already populates.\n\n## Typer changes (src/ir_typer.rs)\n\n- Fold `FnTypes` into `Canonical` (one record per fn).\n- `ModuleTypes::specs: HashMap\u003cFnId, Canonical\u003e` (was composite key).\n- `ModuleTypes::effective_returns: HashMap\u003cFnId, Descr\u003e` (was composite).\n- `entry_seeds` returns one seed per entry FnId — no any-key cohort.\n- `walk_spec_for_discovery::push_key`: drop per-callsite mint; keep\n  ONLY the LUB-merge + histogram bump introduced in fz-7ot.1.\n- SCC + `widen()` at `WIDEN_AT=3` unchanged — same fixpoint machinery,\n  same threshold, driving canonical LUB stability instead of per-spec.\n\n## SpecRegistry changes (src/spec_registry.rs)\n\n- Remove `by_fn: HashMap\u003cFnId, Vec\u003cSpecId\u003e\u003e` field.\n- Remove subsumption tier in `resolve` (lines 99–149) — only the\n  exact-match fast path remains.\n- `resolve(fn_id, _input_descrs)`: input_descrs param retained for\n  caller compat this pass (rip in fz-7ot.3).\n- `register_any_key_at` is now the SOLE registration path; SpecId.0 ==\n  FnId.0 invariant emerges naturally.\n\n## Codegen changes (src/ir_codegen.rs)\n\nDELETE:\n- `tagged_return_specs` build, lines 2795–2867 (~72 lines).\n- `tagged_return_fns` derivation, lines 2873–2880 (~8 lines).\n- `tagged_slot0_cont_specs` + decision flow, lines 2891–2977 (~87 lines).\n- 4 `naturally_opaque` reads at lines 1572, 1606, 2344, 2350: MakeClosure\n  and CallClosure always wire canonical body. Conditional gates collapse.\n- Comment references at lines 2614, 2693, 2747, 2777 — retired analyses.\n\nREPLACE WITH:\n- Per-slot ABI at every emit site: `ArgRepr::from_descr(\u0026canonical[fn].slots[i].descr)`.\n- Per-fn return ABI: `ArgRepr::from_descr(\u0026canonical[fn].return_descr)`.\n\n`reachable_specs` simplifies:\n- Drop the MakeClosure-target blanket seed.\n- Walk callee FnIds from annotated callsites; canonical of every\n  transitively-reachable FnId is reachable. SpecId.0 == FnId.0\n  invariant means the resulting set is FnId-aligned.\n\n## What gets removed\n\n- `fn ensure_any_keys` (src/ir_typer.rs:566).\n- `ModuleTypes::naturally_opaque: HashSet\u003cFnId\u003e` + snapshot logic\n  (lines 234, 517–521).\n- `ModuleTypes::any_key_specs` (lines 217–225).\n- Two-tier `SpecRegistry::resolve` subsumption fallback.\n- `tagged_return_specs`, `tagged_return_fns`, `tagged_slot0_cont_specs`\n  and their propagation loops.\n- Per-callsite specs HashMap composite key throughout.\n- ~64 references to retired bookkeeping across ir_typer + ir_codegen.\n\n## Goldens\n\nRegenerate all 50 fixtures (expected.clif + expected.specs = 100\nfiles) in a single bless pass. Commit message must record:\n- pre/post CLIF line totals (target: majority reduction)\n- pre/post fixture_matrix debug wall time (target: ≤ 20s)\n- pre/post total SpecId count across fixtures (target: ~= total FnId\n  count)\n\n## Acceptance\n\n- All 618 unit + 166 fixture-matrix tests pass with regenerated goldens.\n- Spec count per fixture ≈ FnId count.\n- CLIF lines drop by majority across the fixture set.\n- fixture_matrix debug wall ≤ 20s.\n- No clippy warnings; fmt clean.\n- Annotation arc (fz-aiz.3a–c) unchanged in interface — every annotated\n  callsite still resolves to its canonical's SpecId.\n\n## Honest tradeoffs (re-stated)\n\n- `fib(0, _, 1)` loses its constant-fold spec; routes through\n  canonical body's clause-0 pattern match. A few extra instructions,\n  not a regression worth optimizing absent measurement.\n- Multi-clause fns with one narrow caller per clause may pay one\n  extra branch vs today's narrow-spec model. Targeted refinement\n  follow-up if measurable.\n\n## See also\n\n- fz-7ot.1 — populates the canonical model this ticket consumes.\n- fz-7ot.3 — diagnostic + close fz-t45 + sweep; blocks on this.\n- fz-t45 — TailCallClosure ABI mismatch; dissolves structurally here.",
  "id": "fz-b9b",
  "labels": [],
  "priority": 2,
  "status": "in_progress",
  "title": "fz-7ot.2: demolition — collapse to one spec per fn",
  "type": "task",
  "updated_at": "2026-05-17T23:47:49Z"
}
